<?xml version="1.0"?>
<Model xmlns:xsd="http://www.w3.org/2001/XMLSchema" xmlns:xsi="http://www.w3.org/2001/XMLSchema-instance">
  <ModelName>20250808</ModelName>
  <ModelInfo />
  <ModelPath>C:\Users\user\Desktop\pc기반 파일\Project_EgennamJO\20250808\20250808.xml</ModelPath>
  <InspectImagePath>C:\Users\user\Pictures\chill.jpg</InspectImagePath>
  <InspWindowList>
    <InspWindow>
      <InspWindowType>Base</InspWindowType>
      <Name>Base</Name>
      <UID>BAS_000001</UID>
      <WindowArea>
        <X>83</X>
        <Y>81</Y>
        <Width>116</Width>
        <Height>74</Height>
        <Top>81</Top>
        <Left>83</Left>
        <Location>
          <X>83</X>
          <Y>81</Y>
        </Location>
        <Size>
          <Width>116</Width>
          <Height>74</Height>
        </Size>
      </WindowArea>
      <InspArea>
        <X>0</X>
        <Y>0</Y>
        <Width>0</Width>
        <Height>0</Height>
        <Top>0</Top>
        <Left>0</Left>
        <Location>
          <X>0</X>
          <Y>0</Y>
        </Location>
        <Size>
          <Width>0</Width>
          <Height>0</Height>
        </Size>
      </InspArea>
      <IsTeach>false</IsTeach>
      <InspAlgorithm xsi:type="MatchAlgorithm">
        <InspectType>InspMatch</InspectType>
        <IsUse>true</IsUse>
        <IsInspected>false</IsInspected>
        <TeachRect>
          <X>0</X>
          <Y>0</Y>
          <Width>0</Width>
          <Height>0</Height>
          <Top>0</Top>
          <Left>0</Left>
          <Location>
            <X>0</X>
            <Y>0</Y>
          </Location>
          <Size>
            <Width>0</Width>
            <Height>0</Height>
          </Size>
        </TeachRect>
        <InspRect>
          <X>0</X>
          <Y>0</Y>
          <Width>0</Width>
          <Height>0</Height>
          <Top>0</Top>
          <Left>0</Left>
          <Location>
            <X>0</X>
            <Y>0</Y>
          </Location>
          <Size>
            <Width>0</Width>
            <Height>0</Height>
          </Size>
        </InspRect>
        <ImageChannel>Gray</ImageChannel>
        <ResultString />
        <IsDefect>false</IsDefect>
        <MatchScore>60</MatchScore>
        <ExtSize>
          <Width>100</Width>
          <Height>100</Height>
        </ExtSize>
        <InvertResult>false</InvertResult>
        <OutScore>0</OutScore>
        <OutPoint>
          <X>0</X>
          <Y>0</Y>
        </OutPoint>
        <OutPoints />
        <MatchCount>1</MatchCount>
      </InspAlgorithm>
      <InspAlgorithm xsi:type="BlobAlgorithm">
        <InspectType>InspBinary</InspectType>
        <IsUse>true</IsUse>
        <IsInspected>false</IsInspected>
        <TeachRect>
          <X>0</X>
          <Y>0</Y>
          <Width>0</Width>
          <Height>0</Height>
          <Top>0</Top>
          <Left>0</Left>
          <Location>
            <X>0</X>
            <Y>0</Y>
          </Location>
          <Size>
            <Width>0</Width>
            <Height>0</Height>
          </Size>
        </TeachRect>
        <InspRect>
          <X>0</X>
          <Y>0</Y>
          <Width>0</Width>
          <Height>0</Height>
          <Top>0</Top>
          <Left>0</Left>
          <Location>
            <X>0</X>
            <Y>0</Y>
          </Location>
          <Size>
            <Width>0</Width>
            <Height>0</Height>
          </Size>
        </InspRect>
        <ImageChannel>Gray</ImageChannel>
        <ResultString />
        <IsDefect>false</IsDefect>
        <BinThreshold>
          <lower>100</lower>
          <upper>200</upper>
          <invert>false</invert>
        </BinThreshold>
        <BinMethod>Feature</BinMethod>
        <UseRotatedRect>false</UseRotatedRect>
        <BlobFilters>
          <BlobFilter>
            <name>Area</name>
            <isUse>false</isUse>
            <min>200</min>
            <max>500</max>
          </BlobFilter>
          <BlobFilter>
            <name>width</name>
            <isUse>false</isUse>
            <min>0</min>
            <max>0</max>
          </BlobFilter>
          <BlobFilter>
            <name>Height</name>
            <isUse>false</isUse>
            <min>0</min>
            <max>0</max>
          </BlobFilter>
          <BlobFilter>
            <name>Count</name>
            <isUse>false</isUse>
            <min>0</min>
            <max>0</max>
          </BlobFilter>
        </BlobFilters>
        <OutBlobCount>0</OutBlobCount>
      </InspAlgorithm>
      <InspResultList />
      <IsPatternLearn>true</IsPatternLearn>
    </InspWindow>
    <InspWindow>
      <InspWindowType>Base</InspWindowType>
      <Name>Base</Name>
      <UID>BAS_000002</UID>
      <WindowArea>
        <X>96</X>
        <Y>207</Y>
        <Width>91</Width>
        <Height>51</Height>
        <Top>207</Top>
        <Left>96</Left>
        <Location>
          <X>96</X>
          <Y>207</Y>
        </Location>
        <Size>
          <Width>91</Width>
          <Height>51</Height>
        </Size>
      </WindowArea>
      <InspArea>
        <X>0</X>
        <Y>0</Y>
        <Width>0</Width>
        <Height>0</Height>
        <Top>0</Top>
        <Left>0</Left>
        <Location>
          <X>0</X>
          <Y>0</Y>
        </Location>
        <Size>
          <Width>0</Width>
          <Height>0</Height>
        </Size>
      </InspArea>
      <IsTeach>false</IsTeach>
      <InspAlgorithm xsi:type="MatchAlgorithm">
        <InspectType>InspMatch</InspectType>
        <IsUse>true</IsUse>
        <IsInspected>false</IsInspected>
        <TeachRect>
          <X>0</X>
          <Y>0</Y>
          <Width>0</Width>
          <Height>0</Height>
          <Top>0</Top>
          <Left>0</Left>
          <Location>
            <X>0</X>
            <Y>0</Y>
          </Location>
          <Size>
            <Width>0</Width>
            <Height>0</Height>
          </Size>
        </TeachRect>
        <InspRect>
          <X>0</X>
          <Y>0</Y>
          <Width>0</Width>
          <Height>0</Height>
          <Top>0</Top>
          <Left>0</Left>
          <Location>
            <X>0</X>
            <Y>0</Y>
          </Location>
          <Size>
            <Width>0</Width>
            <Height>0</Height>
          </Size>
        </InspRect>
        <ImageChannel>Gray</ImageChannel>
        <ResultString />
        <IsDefect>false</IsDefect>
        <MatchScore>60</MatchScore>
        <ExtSize>
          <Width>100</Width>
          <Height>100</Height>
        </ExtSize>
        <InvertResult>false</InvertResult>
        <OutScore>0</OutScore>
        <OutPoint>
          <X>0</X>
          <Y>0</Y>
        </OutPoint>
        <OutPoints />
        <MatchCount>1</MatchCount>
      </InspAlgorithm>
      <InspAlgorithm xsi:type="BlobAlgorithm">
        <InspectType>InspBinary</InspectType>
        <IsUse>true</IsUse>
        <IsInspected>false</IsInspected>
        <TeachRect>
          <X>0</X>
          <Y>0</Y>
          <Width>0</Width>
          <Height>0</Height>
          <Top>0</Top>
          <Left>0</Left>
          <Location>
            <X>0</X>
            <Y>0</Y>
          </Location>
          <Size>
            <Width>0</Width>
            <Height>0</Height>
          </Size>
        </TeachRect>
        <InspRect>
          <X>0</X>
          <Y>0</Y>
          <Width>0</Width>
          <Height>0</Height>
          <Top>0</Top>
          <Left>0</Left>
          <Location>
            <X>0</X>
            <Y>0</Y>
          </Location>
          <Size>
            <Width>0</Width>
            <Height>0</Height>
          </Size>
        </InspRect>
        <ImageChannel>Gray</ImageChannel>
        <ResultString />
        <IsDefect>false</IsDefect>
        <BinThreshold>
          <lower>100</lower>
          <upper>200</upper>
          <invert>false</invert>
        </BinThreshold>
        <BinMethod>Feature</BinMethod>
        <UseRotatedRect>false</UseRotatedRect>
        <BlobFilters>
          <BlobFilter>
            <name>Area</name>
            <isUse>false</isUse>
            <min>200</min>
            <max>500</max>
          </BlobFilter>
          <BlobFilter>
            <name>width</name>
            <isUse>false</isUse>
            <min>0</min>
            <max>0</max>
          </BlobFilter>
          <BlobFilter>
            <name>Height</name>
            <isUse>false</isUse>
            <min>0</min>
            <max>0</max>
          </BlobFilter>
          <BlobFilter>
            <name>Count</name>
            <isUse>false</isUse>
            <min>0</min>
            <max>0</max>
          </BlobFilter>
        </BlobFilters>
        <OutBlobCount>0</OutBlobCount>
      </InspAlgorithm>
      <InspResultList />
      <IsPatternLearn>true</IsPatternLearn>
    </InspWindow>
  </InspWindowList>
</Model>